{
  "name": "NPC log",
  "resultPattern": "{lib:formatting#CL}{result}",
  "explanation": "Creates static log entries for NPC records.",
  "date": "2018-03-11",
  "authors": "ELF Vesala.",
  "genre": "universal",
  "categories": [
    "log",
    "character"
  ],
  "tables": [
    {
      "name": "result",
      "explanation": "Verbosity of the resultPattern output.",
      "entries": [
        "{global:startbold}Name{global:endbold}: \r\n\n        {global:startbold}Profession{global:endbold}: \r\n\n        {global:startbold}Background{global:endbold}: \r\n\n        {global:startbold}Relationship{global:endbold}: {global:ssub}(ally, rival, contact, foe, supplier...){global:esub} \r\n\n        {global:startbold}Attitude{global:endbold}: \r\n\n        {global:startbold}Style{global:endbold}: \r\n\n        {global:startbold}Appearance{global:endbold}: \r\n\n        {global:startbold}Speech{global:endbold}: \r\n\n        {global:startbold}Gestures{global:endbold}: \r\n\n        {global:startbold}Behavior{global:endbold}: \r\n\n        {global:startbold}Personality{global:endbold}: \r\n \n        {global:startbold}Goal{global:endbold}: \r\n\n        {global:startbold}Secret{global:endbold}: \r\n"
      ]
    }
  ]
}
